winproxy/commandline.ipynb
winproxy/commandline.py
winproxy/Untitled.py
winproxy/__init__.ipynb
winproxy/__init__.py
winproxy-0.3.0a1.dist-info/DESCRIPTION.rst
winproxy-0.3.0a1.dist-info/entry_points.txt
winproxy-0.3.0a1.dist-info/METADATA
winproxy-0.3.0a1.dist-info/metadata.json
winproxy-0.3.0a1.dist-info/RECORD
winproxy-0.3.0a1.dist-info/top_level.txt
winproxy-0.3.0a1.dist-info/WHEEL
